[
  {
    "image": "1",
    "title": "Банкротство физических лиц",
    "description": "Полное списание <br> всех долгов"
  },
  {
    "image": "2",
    "title": "Защита прав заёмщиков",
    "description": "Юридическая защита интересов клиента"
  },
  {
    "image": "3",
    "title": "Юридическая защита после банкротства",
    "description": "Юридическая помощь после прохождения процедуры"
  },
  {
    "image": "4",
    "title": "Консультация юриста",
    "description": "Полный анализ сложившийся ситуации "
  },
  {
    "image": "5",
    "title": "Ипотечные каникулы",
    "description": "Отсрочка платежей <br> на&nbsp;срок до&nbsp;6 месяцев "
  },
  {
    "image": "6",
    "title": "Защита в суде",
    "description": "Представление интересов в&nbsp;долговых спорах"
  },
  {
    "image": "7",
    "title": "Отказ от&nbsp;взаимодействия с&nbsp;кредиторами",
    "description": "Прекращение звонков и&nbsp;визитов коллекторов*"
  },
  {
    "image": "8",
    "title": "Отмена <br> судебного <br> приказа",
    "description": "Отмена <br> судебного решения*"
  },
  {
    "image": "9",
    "title": "Отзыв согласия на&nbsp;взаимодействие с&nbsp;третьими лицами",
    "description": "Прекращение звонков родственникам, коллегам и&nbsp;т.д.*"
  }
]
